p6_projen_project_awesome_list/__init__.py
p6_projen_project_awesome_list/py.typed
p6_projen_project_awesome_list/_jsii/__init__.py
p6_projen_project_awesome_list/_jsii/p6-projen-project-awesome-list@1.0.21.jsii.tgz
p6_projen_project_awesome_list-1.0.21.dist-info/LICENSE
p6_projen_project_awesome_list-1.0.21.dist-info/METADATA
p6_projen_project_awesome_list-1.0.21.dist-info/WHEEL
p6_projen_project_awesome_list-1.0.21.dist-info/top_level.txt
p6_projen_project_awesome_list-1.0.21.dist-info/RECORD
