Metadata-Version: 2.1
Name: p6-projen-project-awesome-list
Version: 1.0.21
Summary: Projen External Project for awesome-lists
Home-page: https://github.com/p6m7g8/p6-projen-project-awesome-list.git
Author: Philip M. Gollucci<pgollucci@p6m7g8.com>
License: Apache-2.0
Project-URL: Source, https://github.com/p6m7g8/p6-projen-project-awesome-list.git
Platform: UNKNOWN
Classifier: Intended Audience :: Developers
Classifier: Operating System :: OS Independent
Classifier: Programming Language :: JavaScript
Classifier: Programming Language :: Python :: 3 :: Only
Classifier: Programming Language :: Python :: 3.6
Classifier: Programming Language :: Python :: 3.7
Classifier: Programming Language :: Python :: 3.8
Classifier: Programming Language :: Python :: 3.9
Classifier: Typing :: Typed
Classifier: Development Status :: 4 - Beta
Classifier: License :: OSI Approved
Requires-Python: >=3.6
License-File: LICENSE
Requires-Dist: jsii (<2.0.0,>=1.56.0)
Requires-Dist: projen (<0.54.0,>=0.53.9)
Requires-Dist: publication (>=0.0.3)
